amount_extractor/__init__.py
amount_extractor/amount_extractor_app.py
amount_extractor/gui_launcher.py
amount_extractor/assets/gui_image.ico
amount_extractor/assets/gui_logo.png
amount_extractor_app-2.0.1.dist-info/METADATA
amount_extractor_app-2.0.1.dist-info/WHEEL
amount_extractor_app-2.0.1.dist-info/entry_points.txt
amount_extractor_app-2.0.1.dist-info/top_level.txt
amount_extractor_app-2.0.1.dist-info/RECORD
